benchwise/__init__.py
benchwise/cli.py
benchwise/client.py
benchwise/config.py
benchwise/core.py
benchwise/datasets.py
benchwise/metrics.py
benchwise/models.py
benchwise/results.py
benchwise-0.1.0a1.dist-info/METADATA
benchwise-0.1.0a1.dist-info/WHEEL
benchwise-0.1.0a1.dist-info/entry_points.txt
benchwise-0.1.0a1.dist-info/top_level.txt
benchwise-0.1.0a1.dist-info/RECORD
